{
  "updated": "2026-03-15 08:56 EDT",
  "days": {
    "20260315": {
      "date": "Sunday, March 15",
      "games": [
        {
          "league": "Premier League",
          "time": "10:00 AM",
          "match": "Crystal Palace vs Leeds United",
          "source": "Peacock",
          "kick_utc": "2026-03-15T14:00Z"
        },
        {
          "league": "Premier League",
          "time": "10:00 AM",
          "match": "Manchester United vs Aston Villa",
          "source": "USA Network",
          "kick_utc": "2026-03-15T14:00Z"
        },
        {
          "league": "Premier League",
          "time": "10:00 AM",
          "match": "Nottingham Forest vs Fulham",
          "source": "USA Network \u00b7 Peacock",
          "kick_utc": "2026-03-15T14:00Z"
        },
        {
          "league": "Premier League",
          "time": "12:30 PM",
          "match": "Liverpool vs Tottenham Hotspur",
          "source": "USA Network \u00b7 Peacock",
          "kick_utc": "2026-03-15T16:30Z"
        },
        {
          "league": "MLS",
          "time": "2:30 PM",
          "match": "New England Revolution vs FC Cincinnati",
          "source": "Apple TV",
          "kick_utc": "2026-03-15T18:30Z"
        },
        {
          "league": "MLS",
          "time": "4:30 PM",
          "match": "Vancouver Whitecaps vs Minnesota United FC",
          "source": "Apple TV",
          "kick_utc": "2026-03-15T20:30Z"
        },
        {
          "league": "MLS",
          "time": "7:00 PM",
          "match": "San Jose Earthquakes vs Seattle Sounders FC",
          "source": "Apple TV",
          "kick_utc": "2026-03-15T23:00Z"
        },
        {
          "league": "Serie A",
          "time": "7:30 AM",
          "match": "Hellas Verona vs Genoa",
          "source": "CBS / Paramount+",
          "kick_utc": "2026-03-15T11:30Z"
        },
        {
          "league": "Serie A",
          "time": "10:00 AM",
          "match": "Pisa vs Cagliari",
          "source": "CBS / Paramount+",
          "kick_utc": "2026-03-15T14:00Z"
        },
        {
          "league": "Serie A",
          "time": "10:00 AM",
          "match": "Sassuolo vs Bologna",
          "source": "CBS / Paramount+",
          "kick_utc": "2026-03-15T14:00Z"
        },
        {
          "league": "Serie A",
          "time": "1:00 PM",
          "match": "Como vs AS Roma",
          "source": "CBS / Paramount+",
          "kick_utc": "2026-03-15T17:00Z"
        },
        {
          "league": "Serie A",
          "time": "3:45 PM",
          "match": "Lazio vs AC Milan",
          "source": "CBS / Paramount+",
          "kick_utc": "2026-03-15T19:45Z"
        },
        {
          "league": "German Bundesliga",
          "time": "10:30 AM",
          "match": "Werder Bremen vs Mainz",
          "source": "ESPN+",
          "kick_utc": "2026-03-15T14:30Z"
        },
        {
          "league": "German Bundesliga",
          "time": "12:30 PM",
          "match": "SC Freiburg vs 1. FC Union Berlin",
          "source": "ESPN+",
          "kick_utc": "2026-03-15T16:30Z"
        },
        {
          "league": "German Bundesliga",
          "time": "2:30 PM",
          "match": "VfB Stuttgart vs RB Leipzig",
          "source": "ESPN+",
          "kick_utc": "2026-03-15T18:30Z"
        },
        {
          "league": "La Liga",
          "time": "9:00 AM",
          "match": "Mallorca vs Espanyol",
          "source": "ESPN+",
          "kick_utc": "2026-03-15T13:00Z"
        },
        {
          "league": "La Liga",
          "time": "11:15 AM",
          "match": "Barcelona vs Sevilla",
          "source": "ESPN+",
          "kick_utc": "2026-03-15T15:15Z"
        },
        {
          "league": "La Liga",
          "time": "1:30 PM",
          "match": "Real Betis vs Celta Vigo",
          "source": "ESPN+",
          "kick_utc": "2026-03-15T17:30Z"
        },
        {
          "league": "La Liga",
          "time": "4:00 PM",
          "match": "Real Sociedad vs Osasuna",
          "source": "ESPN+",
          "kick_utc": "2026-03-15T20:00Z"
        },
        {
          "league": "Dutch Eredivisie",
          "time": "7:15 AM",
          "match": "FC Twente vs FC Utrecht",
          "source": "ESPN+",
          "kick_utc": "2026-03-15T11:15Z"
        },
        {
          "league": "Dutch Eredivisie",
          "time": "9:30 AM",
          "match": "AZ Alkmaar vs Heracles Almelo",
          "source": "ESPN+",
          "kick_utc": "2026-03-15T13:30Z"
        },
        {
          "league": "Dutch Eredivisie",
          "time": "9:30 AM",
          "match": "Feyenoord Rotterdam vs Excelsior",
          "source": "ESPN+",
          "kick_utc": "2026-03-15T13:30Z"
        },
        {
          "league": "Dutch Eredivisie",
          "time": "11:45 AM",
          "match": "Go Ahead Eagles vs NAC Breda",
          "source": "ESPN+",
          "kick_utc": "2026-03-15T15:45Z"
        },
        {
          "league": "USL League One",
          "time": "6:00 PM",
          "match": "Spokane Velocity FC vs Union Omaha",
          "source": "ESPN+",
          "kick_utc": "2026-03-15T22:00Z"
        }
      ]
    },
    "20260316": {
      "date": "Monday, March 16",
      "games": [
        {
          "league": "Premier League",
          "time": "4:00 PM",
          "match": "Brentford vs Wolverhampton Wanderers",
          "source": "USA Network",
          "kick_utc": "2026-03-16T20:00Z"
        },
        {
          "league": "EFL Championship",
          "time": "4:00 PM",
          "match": "Portsmouth vs Derby County",
          "source": "CBS / Paramount+",
          "kick_utc": "2026-03-16T20:00Z"
        },
        {
          "league": "Serie A",
          "time": "3:45 PM",
          "match": "Cremonese vs Fiorentina",
          "source": "CBS / Paramount+",
          "kick_utc": "2026-03-16T19:45Z"
        },
        {
          "league": "La Liga",
          "time": "4:00 PM",
          "match": "Rayo Vallecano vs Levante",
          "source": "ESPN+",
          "kick_utc": "2026-03-16T20:00Z"
        }
      ]
    },
    "20260317": {
      "date": "Tuesday, March 17",
      "games": [
        {
          "league": "UEFA Champions League",
          "time": "1:45 PM",
          "match": "Sporting CP vs Bodo/Glimt",
          "source": "CBS / Paramount+",
          "kick_utc": "2026-03-17T17:45Z",
          "round_label": "Round of 16 \u00b7 Leg 2"
        },
        {
          "league": "UEFA Champions League",
          "time": "4:00 PM",
          "match": "Arsenal vs Bayer Leverkusen",
          "source": "CBS / Paramount+",
          "kick_utc": "2026-03-17T20:00Z",
          "round_label": "Round of 16 \u00b7 Leg 2"
        },
        {
          "league": "UEFA Champions League",
          "time": "4:00 PM",
          "match": "Chelsea vs Paris Saint-Germain",
          "source": "CBS / Paramount+",
          "kick_utc": "2026-03-17T20:00Z",
          "round_label": "Round of 16 \u00b7 Leg 2"
        },
        {
          "league": "UEFA Champions League",
          "time": "4:00 PM",
          "match": "Manchester City vs Real Madrid",
          "source": "CBS / Paramount+",
          "kick_utc": "2026-03-17T20:00Z",
          "round_label": "Round of 16 \u00b7 Leg 2"
        },
        {
          "league": "CONCACAF Champions Cup",
          "time": "9:00 PM",
          "match": "Alajuelense vs LAFC",
          "source": "FS1",
          "kick_utc": "2026-03-18T01:00Z",
          "round_label": "Round of 16 \u00b7 Leg 2"
        },
        {
          "league": "CONCACAF Champions Cup",
          "time": "11:00 PM",
          "match": "Cruz Azul vs Monterrey",
          "source": "FS1",
          "kick_utc": "2026-03-18T03:00Z",
          "round_label": "Round of 16 \u00b7 Leg 2"
        },
        {
          "league": "EFL Championship",
          "time": "3:45 PM",
          "match": "Watford vs Wrexham",
          "source": "ESPN+",
          "kick_utc": "2026-03-17T19:45Z"
        }
      ]
    },
    "20260318": {
      "date": "Wednesday, March 18",
      "games": [
        {
          "league": "UEFA Champions League",
          "time": "1:45 PM",
          "match": "Barcelona vs Newcastle United",
          "source": "CBS / Paramount+",
          "kick_utc": "2026-03-18T17:45Z",
          "round_label": "Round of 16 \u00b7 Leg 2"
        },
        {
          "league": "UEFA Champions League",
          "time": "4:00 PM",
          "match": "Bayern Munich vs Atalanta",
          "source": "CBS / Paramount+",
          "kick_utc": "2026-03-18T20:00Z",
          "round_label": "Round of 16 \u00b7 Leg 2"
        },
        {
          "league": "UEFA Champions League",
          "time": "4:00 PM",
          "match": "Liverpool vs Galatasaray",
          "source": "CBS / Paramount+",
          "kick_utc": "2026-03-18T20:00Z",
          "round_label": "Round of 16 \u00b7 Leg 2"
        },
        {
          "league": "UEFA Champions League",
          "time": "4:00 PM",
          "match": "Tottenham Hotspur vs Atl\u00e9tico Madrid",
          "source": "CBS / Paramount+",
          "kick_utc": "2026-03-18T20:00Z",
          "round_label": "Round of 16 \u00b7 Leg 2"
        },
        {
          "league": "UEFA Europa League",
          "time": "11:30 AM",
          "match": "Braga vs Ferencvaros",
          "source": "CBS / Paramount+",
          "kick_utc": "2026-03-18T15:30Z",
          "round_label": "Round of 16 \u00b7 Leg 2"
        },
        {
          "league": "CONCACAF Champions Cup",
          "time": "7:00 PM",
          "match": "Inter Miami CF vs Nashville SC",
          "source": "FS1",
          "kick_utc": "2026-03-18T23:00Z",
          "round_label": "Round of 16 \u00b7 Leg 2"
        },
        {
          "league": "CONCACAF Champions Cup",
          "time": "9:00 PM",
          "match": "Am\u00e9rica vs Philadelphia Union",
          "source": "FS1",
          "kick_utc": "2026-03-19T01:00Z",
          "round_label": "Round of 16 \u00b7 Leg 2"
        },
        {
          "league": "CONCACAF Champions Cup",
          "time": "11:00 PM",
          "match": "Seattle Sounders FC vs Vancouver Whitecaps",
          "source": "FS1",
          "kick_utc": "2026-03-19T03:00Z",
          "round_label": "Round of 16 \u00b7 Leg 2"
        },
        {
          "league": "CONCACAF Champions Cup",
          "time": "11:00 PM",
          "match": "Toluca vs San Diego FC",
          "source": "FS2",
          "kick_utc": "2026-03-19T03:00Z",
          "round_label": "Round of 16 \u00b7 Leg 2"
        },
        {
          "league": "EFL Championship",
          "time": "3:45 PM",
          "match": "Southampton vs Norwich City",
          "source": "CBS / Paramount+",
          "kick_utc": "2026-03-18T19:45Z"
        }
      ]
    },
    "20260319": {
      "date": "Thursday, March 19",
      "games": [
        {
          "league": "UEFA Europa League",
          "time": "1:45 PM",
          "match": "FC Midtjylland vs Nottingham Forest",
          "source": "CBS / Paramount+",
          "kick_utc": "2026-03-19T17:45Z",
          "round_label": "Round of 16 \u00b7 Leg 2"
        },
        {
          "league": "UEFA Europa League",
          "time": "1:45 PM",
          "match": "Lyon vs Celta Vigo",
          "source": "CBS / Paramount+",
          "kick_utc": "2026-03-19T17:45Z",
          "round_label": "Round of 16 \u00b7 Leg 2"
        },
        {
          "league": "UEFA Europa League",
          "time": "1:45 PM",
          "match": "SC Freiburg vs Racing Genk",
          "source": "CBS / Paramount+",
          "kick_utc": "2026-03-19T17:45Z",
          "round_label": "Round of 16 \u00b7 Leg 2"
        },
        {
          "league": "UEFA Europa League",
          "time": "4:00 PM",
          "match": "AS Roma vs Bologna",
          "source": "CBS / Paramount+",
          "kick_utc": "2026-03-19T20:00Z",
          "round_label": "Round of 16 \u00b7 Leg 2"
        },
        {
          "league": "UEFA Europa League",
          "time": "4:00 PM",
          "match": "Aston Villa vs Lille",
          "source": "CBS / Paramount+",
          "kick_utc": "2026-03-19T20:00Z",
          "round_label": "Round of 16 \u00b7 Leg 2"
        },
        {
          "league": "UEFA Europa League",
          "time": "4:00 PM",
          "match": "FC Porto vs VfB Stuttgart",
          "source": "CBS / Paramount+",
          "kick_utc": "2026-03-19T20:00Z",
          "round_label": "Round of 16 \u00b7 Leg 2"
        },
        {
          "league": "UEFA Europa League",
          "time": "4:00 PM",
          "match": "Real Betis vs Panathinaikos",
          "source": "CBS / Paramount+",
          "kick_utc": "2026-03-19T20:00Z",
          "round_label": "Round of 16 \u00b7 Leg 2"
        },
        {
          "league": "CONCACAF Champions Cup",
          "time": "7:00 PM",
          "match": "Mount Pleasant FA vs LA Galaxy",
          "source": "FS1",
          "kick_utc": "2026-03-19T23:00Z",
          "round_label": "Round of 16 \u00b7 Leg 2"
        },
        {
          "league": "CONCACAF Champions Cup",
          "time": "9:00 PM",
          "match": "Tigres UANL vs FC Cincinnati",
          "source": "FS1",
          "kick_utc": "2026-03-20T01:00Z",
          "round_label": "Round of 16 \u00b7 Leg 2"
        }
      ]
    }
  }
}